checkgen/__init__.py
checkgen/__main__.py
checkgen/utils.py
checkgen_scochilloff-0.1.0.dist-info/METADATA
checkgen_scochilloff-0.1.0.dist-info/WHEEL
checkgen_scochilloff-0.1.0.dist-info/top_level.txt
checkgen_scochilloff-0.1.0.dist-info/RECORD
