Metadata-Version: 2.1
Name: checkgen_scochilloff
Version: 0.1.0
Summary: Пакет, формирующий чек на основе заказа
Author-email: ScoChillOFF <cheatkiller12@gmail.com>
License: MIT
Requires-Python: >=3.12
